README.md
setup.cfg
setup.py
best_regression_model/__init__.py
best_regression_model/regression_models.py
best_regression_model.egg-info/PKG-INFO
best_regression_model.egg-info/SOURCES.txt
best_regression_model.egg-info/dependency_links.txt
best_regression_model.egg-info/requires.txt
best_regression_model.egg-info/top_level.txt