Metadata-Version: 2.1
Name: best-regression-model
Version: 0.1.1
Summary: It helps to find the best Regression model with the help of the Root Mean Square Value (RMSE) for the given regression model based on the given dataset
Home-page: https://github.com/ronakkkk/best_regression_model
Author: Ronak Bhagchandani
Author-email: rishibhagchandani123@gmail.com
License: Apache License 2.0
Platform: UNKNOWN
